openenv/__init__.py
openenv/cli/__init__.py
openenv/cli/__main__.py
openenv/cli/_cli_utils.py
openenv/cli/_validation.py
openenv/cli/commands/__init__.py
openenv/cli/commands/build.py
openenv/cli/commands/init.py
openenv/cli/commands/push.py
openenv/cli/commands/serve.py
openenv/cli/commands/validate.py
openenv/cli/templates/__init__.py
openenv/cli/templates/openenv_env/README.md
openenv/cli/templates/openenv_env/__init__.py
openenv/cli/templates/openenv_env/client.py
openenv/cli/templates/openenv_env/models.py
openenv/cli/templates/openenv_env/openenv.yaml
openenv/cli/templates/openenv_env/pyproject.toml
openenv/cli/templates/openenv_env/server/Dockerfile
openenv/cli/templates/openenv_env/server/__ENV_NAME___environment.py
openenv/cli/templates/openenv_env/server/__init__.py
openenv/cli/templates/openenv_env/server/app.py
openenv/cli/templates/openenv_env/server/requirements.txt
openenv/core/__init__.py
openenv/core/client_types.py
openenv/core/env_client.py
openenv/core/utils.py
openenv/core/containers/__init__.py
openenv/core/containers/test_local_docker_provider.py
openenv/core/containers/runtime/__init__.py
openenv/core/containers/runtime/providers.py
openenv/core/containers/runtime/uv_provider.py
openenv/core/env_server/__init__.py
openenv/core/env_server/base_transforms.py
openenv/core/env_server/exceptions.py
openenv/core/env_server/http_server.py
openenv/core/env_server/interfaces.py
openenv/core/env_server/route_config.py
openenv/core/env_server/serialization.py
openenv/core/env_server/types.py
openenv/core/env_server/web_interface.py
openenv/core/tools/__init__.py
openenv/core/tools/git_server_client.py
openenv/core/tools/local_python_executor.py
openenv_core/__init__.py
openenv_core-0.2.0.dist-info/licenses/LICENSE
openenv_core-0.2.0.dist-info/METADATA
openenv_core-0.2.0.dist-info/WHEEL
openenv_core-0.2.0.dist-info/entry_points.txt
openenv_core-0.2.0.dist-info/top_level.txt
openenv_core-0.2.0.dist-info/RECORD
