Metadata-Version: 2.4
Name: openenv-core
Version: 0.2.0
Summary: A unified framework for reinforcement learning environments
Requires-Python: >=3.10
License-File: LICENSE
Requires-Dist: fastapi>=0.104.0
Requires-Dist: pydantic>=2.0.0
Requires-Dist: uvicorn>=0.24.0
Requires-Dist: requests>=2.25.0
Requires-Dist: typer>=0.9.0
Requires-Dist: rich>=13.0.0
Requires-Dist: pyyaml>=6.0
Requires-Dist: huggingface_hub>=0.20.0
Requires-Dist: openai>=2.7.2
Requires-Dist: tomli>=2.3.0
Requires-Dist: tomli-w>=1.2.0
Requires-Dist: websockets>=15.0.1
Provides-Extra: core
Requires-Dist: fastapi>=0.104.0; extra == "core"
Requires-Dist: pydantic>=2.0.0; extra == "core"
Requires-Dist: uvicorn>=0.24.0; extra == "core"
Requires-Dist: requests>=2.25.0; extra == "core"
Requires-Dist: websockets>=15.0.1; extra == "core"
Provides-Extra: cli
Requires-Dist: typer>=0.9.0; extra == "cli"
Requires-Dist: rich>=13.0.0; extra == "cli"
Requires-Dist: pyyaml>=6.0; extra == "cli"
Requires-Dist: huggingface_hub>=0.20.0; extra == "cli"
Requires-Dist: openai>=2.7.2; extra == "cli"
Requires-Dist: tomli>=2.3.0; extra == "cli"
Requires-Dist: tomli-w>=1.2.0; extra == "cli"
Provides-Extra: all
Requires-Dist: openenv[core]; extra == "all"
Requires-Dist: openenv[cli]; extra == "all"
Dynamic: license-file
